cascata/__init__.py
cascata/_async_queue.cpp
cascata/_async_queue.cpython-310-x86_64-linux-gnu.so
cascata/channel.py
cascata/component.py
cascata/graph.py
cascata/log.py
cascata/port.py
cascata-0.1.8.dist-info/METADATA
cascata-0.1.8.dist-info/WHEEL
cascata-0.1.8.dist-info/top_level.txt
cascata-0.1.8.dist-info/RECORD
cascata-0.1.8.dist-info/licenses/LICENSE
