Metadata-Version: 2.4
Name: cascata
Version: 0.1.8
Summary: An asynchronous, multicore graph execution framework for Python.
Home-page: https://github.com/simacleod/Cascata
Author: Stuart MacLeod
Author-email: orangootan@gmail.com
License: MIT
Project-URL: Bug Tracker, https://github.com/simacleod/Cascata/issues
Classifier: Programming Language :: Python :: 3
Classifier: Programming Language :: Python :: 3.10
Classifier: Programming Language :: Python :: 3.11
Classifier: Programming Language :: Python :: 3.12
Classifier: Programming Language :: Python :: 3.13
Classifier: License :: OSI Approved :: MIT License
Classifier: Operating System :: POSIX :: Linux
Classifier: Intended Audience :: Developers
Classifier: Topic :: Software Development :: Libraries
Classifier: Framework :: AsyncIO
Requires-Python: >=3.10
License-File: LICENSE
Requires-Dist: multiprocess
Requires-Dist: dill
Requires-Dist: aioprocessing
Requires-Dist: aioitertools
Requires-Dist: networkx
Dynamic: author
Dynamic: author-email
Dynamic: classifier
Dynamic: description
Dynamic: description-content-type
Dynamic: home-page
Dynamic: license
Dynamic: license-file
Dynamic: project-url
Dynamic: requires-dist
Dynamic: requires-python
Dynamic: summary
